goatl/__init__.py
goatl/core.py
goatl/utils.py
goatl-0.6.5.dist-info/LICENSE
goatl-0.6.5.dist-info/WHEEL
goatl-0.6.5.dist-info/METADATA
goatl-0.6.5.dist-info/RECORD
