Metadata-Version: 2.1
Name: goatl
Version: 0.6.5
Summary: The goat logger
Home-page: https://github.com/EytanDn/goatl
License: MIT
Keywords: logging,logger,log,goat,goatl,goatlogger,goat-logger,goat-logging,goat-log
Author: goatl
Author-email: EytanDn@gmail.com
Requires-Python: >=3.8,<4.0
Classifier: Development Status :: 3 - Alpha
Classifier: Intended Audience :: Developers
Classifier: License :: OSI Approved :: MIT License
Classifier: Operating System :: OS Independent
Classifier: Programming Language :: Python :: 3
Classifier: Programming Language :: Python :: 3.10
Classifier: Programming Language :: Python :: 3.11
Classifier: Programming Language :: Python :: 3.8
Classifier: Programming Language :: Python :: 3.9
Classifier: Topic :: Software Development :: Libraries :: Python Modules
Project-URL: Repository, https://github.com/EytanDn/goatl
